stixorm/__init__.py
stixorm/module/__init__.py
stixorm/module/authorise.py
stixorm/module/definitions/__init__.py
stixorm/module/definitions/attack/__init__.py
stixorm/module/definitions/attack/base/attack_base.json
stixorm/module/definitions/attack/classes.py
stixorm/module/definitions/attack/data/attack-campaign.json
stixorm/module/definitions/attack/data/attack-group.json
stixorm/module/definitions/attack/data/attack-identity.json
stixorm/module/definitions/attack/data/attack-relation.json
stixorm/module/definitions/attack/data/collection.json
stixorm/module/definitions/attack/data/data-component.json
stixorm/module/definitions/attack/data/data-source.json
stixorm/module/definitions/attack/data/matrix.json
stixorm/module/definitions/attack/data/mitigation.json
stixorm/module/definitions/attack/data/software-malware.json
stixorm/module/definitions/attack/data/software-tool.json
stixorm/module/definitions/attack/data/sub-technique.json
stixorm/module/definitions/attack/data/tactic.json
stixorm/module/definitions/attack/data/technique.json
stixorm/module/definitions/attack/mappings/is_list_meta.json
stixorm/module/definitions/attack/mappings/is_list_sco.json
stixorm/module/definitions/attack/mappings/is_list_sdo.json
stixorm/module/definitions/attack/mappings/is_list_sro.json
stixorm/module/definitions/attack/mappings/is_list_sub_objects.json
stixorm/module/definitions/attack/mappings/object_conversion.json
stixorm/module/definitions/attack/mappings/relations_embedded.json
stixorm/module/definitions/attack/mappings/relations_list_of_objects.json
stixorm/module/definitions/attack/mappings/relations_sro_roles.json
stixorm/module/definitions/attack/schema/cti-attack-rules.tql
stixorm/module/definitions/attack/schema/cti-attack.tql
stixorm/module/definitions/attack/sub_objects/object-version.json
stixorm/module/definitions/cacao/__init__.py
stixorm/module/definitions/cacao/classes.py
stixorm/module/definitions/cacao/mappings/is_list_sub_objects.json
stixorm-0.3.9.dist-info/LICENSE
stixorm-0.3.9.dist-info/METADATA
stixorm-0.3.9.dist-info/WHEEL
stixorm-0.3.9.dist-info/RECORD
