Metadata-Version: 2.1
Name: stixorm
Version: 0.3.9
Summary: Description
Home-page: https://github.com/os-threat/Stix-ORM
Author: Brett Forbes
Author-email: brett@cloudaccelerator.co
Requires-Python: >=3.8.1,<4.0.0
Classifier: Development Status :: 3 - Alpha
Classifier: License :: OSI Approved :: Apache Software License
Classifier: Operating System :: OS Independent
Classifier: Programming Language :: Python :: 3
Classifier: Programming Language :: Python :: 3.9
Classifier: Programming Language :: Python :: 3.10
Classifier: Programming Language :: Python :: 3.11
Classifier: Programming Language :: Python :: 3.12
Classifier: Topic :: Utilities
Requires-Dist: loguru (>=0.7.0,<0.8.0)
Requires-Dist: networkx (>=3.1,<4.0)
Requires-Dist: pydantic (>=2.1.1,<3.0.0)
Requires-Dist: stix2 (==3.0.1)
Requires-Dist: typedb-driver (>=2.25.6,<3.0.0)
Requires-Dist: validators (>=0.20.0,<0.21.0)
Project-URL: Repository, https://github.com/os-threat/Stix-ORM
